{
  "version": "1.1.1",
  "windows": {
    "worker": {},
    "main": {
      "main": true,
      "url": "app://editor/index.html",
      "windowType": "dockable",
      "x": 0,
      "y": 23,
      "width": 1440,
      "height": 808,
      "layout": {
        "children": [
          {
            "children": [
              {
                "active": 0,
                "children": [
                  "hierarchy"
                ],
                "height": 360.453125,
                "type": "panel",
                "width": 232.71875
              },
              {
                "active": 0,
                "children": [
                  "assets"
                ],
                "height": 363.546875,
                "type": "panel",
                "width": 232.71875
              }
            ],
            "height": 726,
            "type": "dock-v",
            "width": 232.71875
          },
          {
            "children": [
              {
                "children": [
                  {
                    "active": 0,
                    "children": [
                      "scene"
                    ],
                    "height": 450.828125,
                    "type": "panel",
                    "width": 554.28125
                  },
                  {
                    "active": 0,
                    "children": [
                      "node-library"
                    ],
                    "height": 450.828125,
                    "type": "panel",
                    "width": 300.78125
                  }
                ],
                "height": 450.828125,
                "type": "dock-h",
                "width": 857.0625
              },
              {
                "active": 0,
                "children": [
                  "console",
                  "timeline",
                  "game-window"
                ],
                "height": 273.171875,
                "type": "panel",
                "width": 857.0625
              }
            ],
            "height": 726,
            "type": "dock-v",
            "width": 857.0625
          },
          {
            "active": 0,
            "children": [
              "inspector",
              "cocos-services"
            ],
            "height": 726,
            "type": "panel",
            "width": 346.234375
          }
        ],
        "type": "dock-h"
      },
      "panels": [
        "hierarchy",
        "assets",
        "node-library",
        "console",
        "timeline",
        "game-window",
        "inspector",
        "cocos-services",
        "scene"
      ]
    }
  },
  "panels": {
    "preferences": {
      "x": 468,
      "y": 128,
      "width": 601,
      "height": 566
    }
  }
}